sinapsis_huggingface_diffusers/__init__.py
sinapsis_huggingface_diffusers/helpers/__init__.py
sinapsis_huggingface_diffusers/helpers/tags.py
sinapsis_huggingface_diffusers/templates/__init__.py
sinapsis_huggingface_diffusers/templates/base_diffusers.py
sinapsis_huggingface_diffusers/templates/image_to_image_diffusers.py
sinapsis_huggingface_diffusers/templates/image_to_video_gen_xl_diffusers.py
sinapsis_huggingface_diffusers/templates/inpainting_diffusers.py
sinapsis_huggingface_diffusers/templates/text_to_image_diffusers.py
sinapsis_huggingface_diffusers-0.1.11.dist-info/licenses/LICENSE
sinapsis_huggingface_diffusers-0.1.11.dist-info/METADATA
sinapsis_huggingface_diffusers-0.1.11.dist-info/WHEEL
sinapsis_huggingface_diffusers-0.1.11.dist-info/top_level.txt
sinapsis_huggingface_diffusers-0.1.11.dist-info/RECORD
