Metadata-Version: 2.4
Name: sinapsis-huggingface-diffusers
Version: 0.1.11
Summary: Templates for HuggingFace Diffusers, supporting text-to-image, image-to-image, video generation, and inpainting workflows.
Author-email: SinapsisAI <dev@sinapsis.tech>
Project-URL: Homepage, https://sinapsis.tech
Project-URL: Documentation, https://docs.sinapsis.tech/docs
Project-URL: Tutorials, https://docs.sinapsis.tech/tutorials
Project-URL: Repository, https://github.com/Sinapsis-AI/sinapsis-huggingface.git
Requires-Python: >=3.10
License-File: LICENSE
Requires-Dist: accelerate>=1.1.1
Requires-Dist: diffusers>=0.31.0
Requires-Dist: opencv-python-headless>=4.11.0.86
Requires-Dist: sinapsis>=0.1.1
Requires-Dist: torch>=2.5.1
Requires-Dist: transformers>=4.47.1
Provides-Extra: sinapsis-image-transforms
Requires-Dist: sinapsis-albumentations>=0.1.1; extra == "sinapsis-image-transforms"
Provides-Extra: all
Requires-Dist: sinapsis-huggingface-diffusers[sinapsis-image-transforms]; extra == "all"
Dynamic: license-file
